crushha/__init__.py
crushha/interpreter.py
crushha-0.2.dist-info/DESCRIPTION.rst
crushha-0.2.dist-info/METADATA
crushha-0.2.dist-info/RECORD
crushha-0.2.dist-info/WHEEL
crushha-0.2.dist-info/metadata.json
crushha-0.2.dist-info/top_level.txt
crushha-0.2.dist-info/zip-safe
