Metadata-Version: 2.0
Name: crushha
Version: 0.2
Summary: Define HA domains with CRUSH maps
Home-page: http://blitz.works/crushha
Author: Da_Blitz
Author-email: code@pocketnix.org
License: ISC
Download-URL: http://blitz.works/crushha/archive/tip.zip
Keywords: crush CRUSH ha ceph containers
Platform: UNKNOWN
Classifier: Development Status :: 3 - Alpha
Classifier: Intended Audience :: Developers
Classifier: License :: OSI Approved :: ISC License (ISCL)
Classifier: Operating System :: OS Independent
Classifier: Programming Language :: Python :: 3.3
Classifier: Topic :: Software Development :: Interpreters
Classifier: Topic :: Software Development :: Libraries
Classifier: Topic :: System :: Clustering
Classifier: Topic :: System :: Distributed Computing
